laissez/__init__.py
laissez-0.1.0.dist-info/METADATA
laissez-0.1.0.dist-info/WHEEL
laissez-0.1.0.dist-info/entry_points.txt
laissez-0.1.0.dist-info/licenses/LICENSE
laissez-0.1.0.dist-info/RECORD
