Metadata-Version: 2.4
Name: laissez
Version: 0.1.0
Summary: Agent spending you trust
Author-email: Matthew Collins <matthew@noeticos.com>
License-File: LICENSE
Requires-Python: >=3.10
